advans_erp_checker.py
Advans_ERP_Checker-0.1.1.dist-info/LICENSE
Advans_ERP_Checker-0.1.1.dist-info/METADATA
Advans_ERP_Checker-0.1.1.dist-info/WHEEL
Advans_ERP_Checker-0.1.1.dist-info/top_level.txt
Advans_ERP_Checker-0.1.1.dist-info/RECORD
